{
  "title": "인과효과 추론 (Causal Inference)",
  "subtitle": "서울대학교 행정대학원 고길곤",
  "description": "이 책은 인과효과 추론 강의를 위해 준비했습니다. 계속 수정중인 원고입니다",
  "lead": "상업적인 용도로 사용하지 않고 좋은 의견 제시해주시기 바랍니다(kilkon@snu.ac.kr)",
  "parts": [
    {
      "id": "part-1",
      "title": "제1부 | 인과이론의 기본 개념",
      "description": "",
      "chapters": [
        {
          "slug": "ch01-01-correlation-causation",
          "source": "chapters/ch01-01-correlation-causation.md",
          "label": "",
          "title": "1.1 상관과 인과의 근본적 차이 — 왜 회귀만으로는 부족한가"
        },
        {
          "slug": "ch01-02-counterfactuals",
          "source": "chapters/ch01-02-counterfactuals.md",
          "label": "",
          "title": "1.2 반사실(counterfactual)의 정의와 직관적 예시"
        },
        {
          "slug": "ch01-03-ladder",
          "source": "chapters/ch01-03-ladder.md",
          "label": "",
          "title": "1.3 인과 사다리와 구조 인과 모형 — 세 층위의 형식화"
        },
        {
          "slug": "ch01-04-gender-causality-debate",
          "source": "chapters/ch01-04-gender-causality-debate.md",
          "label": "",
          "title": "1.4 성별은 원인이 될 수 없는가 — 비판적 검토"
        },
        {
          "slug": "ch02-00-potential-outcomes-framework-overview",
          "source": "chapters/ch02-00-potential-outcomes-framework-overview.md",
          "label": "2",
          "title": "2장. 잠재결과 프레임워크 — 전체 방향과 학습 로드맵"
        },
        {
          "slug": "ch02-01-unit-treatment-potential-outcomes",
          "source": "chapters/ch02-01-unit-treatment-potential-outcomes.md",
          "label": "",
          "title": "2.1 단위 · 처치 · 잠재결과의 정의"
        },
        {
          "slug": "ch02-02-ice-ate-att-atc",
          "source": "chapters/ch02-02-ice-ate-att-atc.md",
          "label": "",
          "title": "2.2 개인 인과효과와 평균 인과효과 — ICE · ATE · ATT · ATC"
        },
        {
          "slug": "ch02-03-sutva-missingness",
          "source": "chapters/ch02-03-sutva-missingness.md",
          "label": "",
          "title": "2.3 SUTVA, 결측 데이터 관점, 형식적 통합"
        },
        {
          "slug": "ch02-04-generalization-target-population",
          "source": "chapters/ch02-04-generalization-target-population.md",
          "label": "",
          "title": "2.4 일반화 가능성과 표적 모집단"
        },
        {
          "slug": "ch03-00-modeling-identification-intro",
          "source": "chapters/ch03-00-modeling-identification-intro.md",
          "label": "3",
          "title": "3장. 모형 설정, 식별, 추정"
        },
        {
          "slug": "ch03-01-specification-identification-estimation",
          "source": "chapters/ch03-01-specification-identification-estimation.md",
          "label": "3.1",
          "title": "3.1 모형 설정, 식별, 추정의 구분"
        },
        {
          "slug": "ch03-02-scm-dag-model-specification",
          "source": "chapters/ch03-02-scm-dag-model-specification.md",
          "label": "3.2",
          "title": "3.2 ??? ??? ?? - Lewbel? Identification Zoo"
        },
        {
          "slug": "ch03-03-identification-observed-to-causal",
          "source": "chapters/ch03-03-identification-observed-to-causal.md",
          "label": "3.3",
          "title": "3.3 식별: 관측분포와 인과량의 연결"
        },
        {
          "slug": "ch03-04-estimation-sample-implementation",
          "source": "chapters/ch03-04-estimation-sample-implementation.md",
          "label": "3.4",
          "title": "3.4 추정: 식별된 표현의 표본 구현"
        },
        {
          "slug": "ch03-05-why-distinction-chapter3",
          "source": "chapters/ch03-05-why-distinction-chapter3.md",
          "label": "3.5",
          "title": "3.5 3장에서 왜 이 구분이 필요한가"
        },
        {
          "slug": "ch04-01-dag-bias-structure",
          "source": "chapters/ch04-01-dag-bias-structure.md",
          "label": "4",
          "title": "4장. DAG로 읽는 편향의 구조"
        },
        {
          "slug": "ch04-02-s041",
          "source": "chapters/ch04-02-s041.md",
          "label": "",
          "title": "4.1 경로의 세 원형: 포크(fork) · 파이프(pipe) · 콜라이더(collider)"
        },
        {
          "slug": "ch04-03-s042",
          "source": "chapters/ch04-03-s042.md",
          "label": "",
          "title": "4.2 조상 · 자손 · 조건화(conditioning)의 효과"
        },
        {
          "slug": "ch04-04-s043",
          "source": "chapters/ch04-04-s043.md",
          "label": "",
          "title": "4.3 백도어(backdoor) 기준과 프론트도어(frontdoor) 기준 — 직관과 공식"
        },
        {
          "slug": "ch04-05-s044",
          "source": "chapters/ch04-05-s044.md",
          "label": "",
          "title": "4.4 조정 공식(adjustment formula)과 식별(identification)의 개념"
        },
        {
          "slug": "ch04-05a-s044a",
          "source": "chapters/ch04-05a-s044a.md",
          "label": "",
          "title": "4.5 내생적 선택편향(endogenous selection bias)과 유형별 구조"
        },
        {
          "slug": "ch04-06-s045",
          "source": "chapters/ch04-06-s045.md",
          "label": "",
          "title": "4.6 콜라이더(충돌) 편향의 방향·크기 — 문헌 개관"
        },
        {
          "slug": "homophily_bias",
          "source": "chapters/homophily_bias.md",
          "label": "4.7",
          "title": "4.7 Homophily bias(??? ??)"
        }
      ]
    },
    {
      "id": "part-2",
      "title": "제2부 | 실험과 내적 타당도",
      "description": "무작위 실험을 인과추론의 기준점으로 이해하고 그 가정과 한계를 정리합니다.",
      "chapters": [
        {
          "slug": "ch06-01-randomization-identification",
          "source": "chapters/ch06-01-randomization-identification.md",
          "label": "6",
          "title": "6.1 장의 핵심 항목"
        },
        {
          "slug": "ch06-02-s061",
          "source": "chapters/ch06-02-s061.md",
          "label": "",
          "title": "6.1.1 무작위화가 교란을 제거하는 메커니즘 — DAG로 보기"
        },
        {
          "slug": "ch06-03-s062",
          "source": "chapters/ch06-03-s062.md",
          "label": "",
          "title": "6.1.2 ATE의 비편향 추정량으로서의 차이-in-means"
        },
        {
          "slug": "ch06-04-s063",
          "source": "chapters/ch06-04-s063.md",
          "label": "",
          "title": "6.1.3 실험 설계의 변형: 층화 · 군집 · 요인 설계"
        },
        {
          "slug": "ch07-01-compliance-itt-cace",
          "source": "chapters/ch07-01-compliance-itt-cace.md",
          "label": "7",
          "title": "7장. 순응, ITT, CACE와 실험의 내적 타당도"
        },
        {
          "slug": "ch07-02-s071",
          "source": "chapters/ch07-02-s071.md",
          "label": "7.1",
          "title": "7.1 완전 순응 vs. 부분 순응: 처치 배정과 처치 수령의 구분"
        },
        {
          "slug": "ch07-03-s072",
          "source": "chapters/ch07-03-s072.md",
          "label": "7.2",
          "title": "7.2 ITT와 CACE/LATE의 정의와 차이"
        },
        {
          "slug": "ch07-04-s073",
          "source": "chapters/ch07-04-s073.md",
          "label": "7.3",
          "title": "7.3 도구변수로서의 무작위 배정과 단조성 가정"
        },
        {
          "slug": "ch07-05-s074",
          "source": "chapters/ch07-05-s074.md",
          "label": "7.4",
          "title": "7.4 이탈자(attrition)와 무응답 처리 전략"
        },
        {
          "slug": "ch08-01-external-validity-transportability",
          "source": "chapters/ch08-01-external-validity-transportability.md",
          "label": "8",
          "title": "8?. ?? ???, ?? ???, ??? ???? ??"
        },
        {
          "slug": "ch08-02-s081",
          "source": "chapters/ch08-02-s081.md",
          "label": "8.1",
          "title": "8.1 ?? ???? ?? ???? ??"
        },
        {
          "slug": "ch08-03-s082",
          "source": "chapters/ch08-03-s082.md",
          "label": "8.2",
          "title": "8.2 ?? ??? ?? ???? ???"
        },
        {
          "slug": "ch08-04-s083",
          "source": "chapters/ch08-04-s083.md",
          "label": "8.3",
          "title": "8.3 ?? ??? ???? transportability"
        },
        {
          "slug": "ch08-05-s084",
          "source": "chapters/ch08-05-s084.md",
          "label": "8.4",
          "title": "8.4 ????? ????? ??"
        }
      ]
    },
    {
      "id": "part-3",
      "title": "?3? | ????? ?? ???? ???",
      "description": "????? ? ????? ??? ????, ????????????????? ??? ???? ?????.",
      "chapters": [
        {
          "slug": "ch10-01-covariate-control-limits",
          "source": "chapters/ch10-01-covariate-control-limits.md",
          "label": "10",
          "title": "10?. ??, ??, ??? ??"
        },
        {
          "slug": "ch10-02-s101",
          "source": "chapters/ch10-02-s101.md",
          "label": "10.1",
          "title": "10.1 ????? ????"
        },
        {
          "slug": "ch10-03-s102",
          "source": "chapters/ch10-03-s102.md",
          "label": "10.2",
          "title": "10.2 ????? ??: MCAR, MAR, MNAR"
        },
        {
          "slug": "ch10-04-s103",
          "source": "chapters/ch10-04-s103.md",
          "label": "10.3",
          "title": "10.3 ??? ????? ?? ??"
        },
        {
          "slug": "ch11-01-collider-bias",
          "source": "chapters/ch11-01-collider-bias.md",
          "label": "11",
          "title": "11?. ??, ???, ????"
        },
        {
          "slug": "ch11-02-s111",
          "source": "chapters/ch11-02-s111.md",
          "label": "11.1",
          "title": "11.1 ?? ??? ????"
        },
        {
          "slug": "ch11-03-s112",
          "source": "chapters/ch11-03-s112.md",
          "label": "11.2",
          "title": "11.2 ??? ??, ???, ????"
        },
        {
          "slug": "ch11-04-s113",
          "source": "chapters/ch11-04-s113.md",
          "label": "11.3",
          "title": "11.3 ????, ????, ??? ????"
        },
        {
          "slug": "ch12-01-unobserved-confounding-limits",
          "source": "chapters/ch12-01-unobserved-confounding-limits.md",
          "label": "12",
          "title": "12?. ??, ??, ?? ??? ??"
        },
        {
          "slug": "ch12-02-s121",
          "source": "chapters/ch12-02-s121.md",
          "label": "12.1",
          "title": "12.1 ??? spillover: SUTVA? ??"
        },
        {
          "slug": "ch12-03-s122",
          "source": "chapters/ch12-03-s122.md",
          "label": "12.2",
          "title": "12.2 ????? ???? implementation heterogeneity"
        },
        {
          "slug": "ch12-04-s123",
          "source": "chapters/ch12-04-s123.md",
          "label": "12.3",
          "title": "12.3 ????, ???? ??, ??? ??"
        }
      ]
    },
    {
      "id": "part-4",
      "title": "제4부 | 조건부 독립과 준실험의 식별 전략",
      "description": "조건부 독립, 도구변수, 회귀불연속, DID, 패널모형을 통해 관측 자료에서 식별을 시도하는 전략을 다룹니다.",
      "chapters": [
        {
          "slug": "ch13-01-regression-matching-ipw",
          "source": "chapters/ch13-01-regression-matching-ipw.md",
          "label": "13",
          "title": "13.1 장의 핵심 항목"
        },
        {
          "slug": "ch13-02-s131",
          "source": "chapters/ch13-02-s131.md",
          "label": "",
          "title": "13.1.1 조건부 독립 가정(CIA / ignorability)의 의미"
        },
        {
          "slug": "ch13-03-s132",
          "source": "chapters/ch13-03-s132.md",
          "label": "",
          "title": "13.1.2 회귀 조정의 인과적 해석 조건"
        },
        {
          "slug": "ch13-04-s133",
          "source": "chapters/ch13-04-s133.md",
          "label": "",
          "title": "13.1.3 매칭의 직관 — 이웃 매칭 · 성향점수 매칭 · 칼퍼 반경"
        },
        {
          "slug": "ch13-05-s134",
          "source": "chapters/ch13-05-s134.md",
          "label": "",
          "title": "13.1.4 역확률가중(IPW)과 안정화 가중(SIPW)"
        },
        {
          "slug": "ch13-06-s135",
          "source": "chapters/ch13-06-s135.md",
          "label": "",
          "title": "13.1.5 공통 지지(common support) — 외삽 위험과 진단"
        },
        {
          "slug": "ch14-00-instrumental-variables-intro",
          "source": "chapters/ch14-00-instrumental-variables-intro.md",
          "label": "14",
          "title": "14장. 도구변수 접근법"
        },
        {
          "slug": "ch14-01-instrumental-variables",
          "source": "chapters/ch14-01-instrumental-variables.md",
          "label": "",
          "title": "14.1 IV의 세 가지 핵심 가정"
        },
        {
          "slug": "ch14-02-s142",
          "source": "chapters/ch14-02-s142.md",
          "label": "",
          "title": "14.2 Wald 추정량과 2SLS"
        },
        {
          "slug": "ch14-03-s143",
          "source": "chapters/ch14-03-s143.md",
          "label": "",
          "title": "14.3 LATE 해석"
        },
        {
          "slug": "ch14-04-s144",
          "source": "chapters/ch14-04-s144.md",
          "label": "",
          "title": "14.4 약한 도구 진단과 대응"
        },
        {
          "slug": "ch14-05-s145",
          "source": "chapters/ch14-05-s145.md",
          "label": "",
          "title": "14.5 자연실험형 IV 예시"
        },
        {
          "slug": "ch15-00-rdd-intro",
          "source": "chapters/ch15-00-rdd-intro.md",
          "label": "15",
          "title": "15장. 회귀불연속 설계"
        },
        {
          "slug": "ch15-01-rdd",
          "source": "chapters/ch15-01-rdd.md",
          "label": "",
          "title": "15.1 배정변수와 임계값의 역할"
        },
        {
          "slug": "ch15-02-s152",
          "source": "chapters/ch15-02-s152.md",
          "label": "",
          "title": "15.2 Sharp RDD: 연속성 가정과 국소 효과"
        },
        {
          "slug": "ch15-03-s153",
          "source": "chapters/ch15-03-s153.md",
          "label": "",
          "title": "15.3 Fuzzy RDD: IV로의 환원"
        },
        {
          "slug": "ch15-04-s154",
          "source": "chapters/ch15-04-s154.md",
          "label": "",
          "title": "15.4 연속 처치·다중 임계값 확장"
        },
        {
          "slug": "ch15-05-s155",
          "source": "chapters/ch15-05-s155.md",
          "label": "",
          "title": "15.5 조작 검정과 진단 시각화"
        },
        {
          "slug": "ch16-00-did-intro",
          "source": "chapters/ch16-00-did-intro.md",
          "label": "16",
          "title": "16장. 이중차분법"
        },
        {
          "slug": "ch16-01-did",
          "source": "chapters/ch16-01-did.md",
          "label": "",
          "title": "16.1 DiD의 기본 직관과 2x2 설계"
        },
        {
          "slug": "ch16-02-s162",
          "source": "chapters/ch16-02-s162.md",
          "label": "",
          "title": "16.2 회귀 표현과 패널자료에서의 DID"
        },
        {
          "slug": "ch16-03-s163",
          "source": "chapters/ch16-03-s163.md",
          "label": "",
          "title": "16.3 동태적 효과와 이벤트 스터디(event-study)"
        },
        {
          "slug": "ch16-04-s164",
          "source": "chapters/ch16-04-s164.md",
          "label": "",
          "title": "16.4 스태거드 도입과 현대적 DID"
        },
        {
          "slug": "ch16-05-s165",
          "source": "chapters/ch16-05-s165.md",
          "label": "",
          "title": "16.5 평행추세와 핵심 가정, 진단"
        },
        {
          "slug": "ch17-00-panel-models-intro",
          "source": "chapters/ch17-00-panel-models-intro.md",
          "label": "17",
          "title": "17장. 패널모형"
        },
        {
          "slug": "ch17-01-panel-fixed-effects",
          "source": "chapters/ch17-01-panel-fixed-effects.md",
          "label": "",
          "title": "17.1 FE의 기본 설정과 인과 해석"
        },
        {
          "slug": "ch17-02-s172",
          "source": "chapters/ch17-02-s172.md",
          "label": "",
          "title": "17.2 FE가 제거하는 것과 제거하지 못하는 것"
        },
        {
          "slug": "ch17-03-s173",
          "source": "chapters/ch17-03-s173.md",
          "label": "",
          "title": "17.3 시간 고정효과와 이중 고정효과(TWFE)의 해석"
        },
        {
          "slug": "ch17-04-s174",
          "source": "chapters/ch17-04-s174.md",
          "label": "",
          "title": "17.4 FE 인과 해석의 조건과 진단"
        }
      ]
    },
    {
      "id": "part-5",
      "title": "제5부 | 이질성 · 매개 · 강건성",
      "description": "효과의 이질성, 매개경로, 민감도와 강건성 점검을 다룹니다.",
      "chapters": [
        {
          "slug": "ch18-00-cate-intro",
          "source": "chapters/ch18-00-cate-intro.md",
          "label": "18",
          "title": "18장. 조건부 평균처치효과"
        },
        {
          "slug": "ch18-01-heterogeneous-treatment-effects",
          "source": "chapters/ch18-01-heterogeneous-treatment-effects.md",
          "label": "",
          "title": "18.1 CATE의 정의와 식별"
        },
        {
          "slug": "ch18-02-s182",
          "source": "chapters/ch18-02-s182.md",
          "label": "",
          "title": "18.2 서브그룹 분석의 위험"
        },
        {
          "slug": "ch18-03-s183",
          "source": "chapters/ch18-03-s183.md",
          "label": "",
          "title": "18.3 효과 수정자와 교란변수"
        },
        {
          "slug": "ch18-04-s184",
          "source": "chapters/ch18-04-s184.md",
          "label": "",
          "title": "18.4 개인화 처치 규칙(ITR)"
        },
        {
          "slug": "ch19-00-mediation-intro",
          "source": "chapters/ch19-00-mediation-intro.md",
          "label": "19",
          "title": "19장. 매개효과분석"
        },
        {
          "slug": "ch19-01-mediation-effects",
          "source": "chapters/ch19-01-mediation-effects.md",
          "label": "",
          "title": "19.1 총효과, 직접효과, 간접효과의 분해"
        },
        {
          "slug": "ch19-02-s192",
          "source": "chapters/ch19-02-s192.md",
          "label": "",
          "title": "19.2 자연 직접효과와 자연 간접효과의 정의와 식별"
        },
        {
          "slug": "ch19-03-s193",
          "source": "chapters/ch19-03-s193.md",
          "label": "",
          "title": "19.3 교차세계 반사실과 처치 이후 교란"
        },
        {
          "slug": "ch19-04-s194",
          "source": "chapters/ch19-04-s194.md",
          "label": "",
          "title": "19.4 민감도 분석과 강건성 보고"
        },
        {
          "slug": "ch20-00-sensitivity-intro",
          "source": "chapters/ch20-00-sensitivity-intro.md",
          "label": "20",
          "title": "20장. 민감도 분석"
        },
        {
          "slug": "ch20-01-sensitivity-partial-identification",
          "source": "chapters/ch20-01-sensitivity-partial-identification.md",
          "label": "",
          "title": "20.1 Rosenbaum 경계와 \\(\\Gamma\\)-민감도"
        },
        {
          "slug": "ch20-02-s202",
          "source": "chapters/ch20-02-s202.md",
          "label": "",
          "title": "20.2 E-value: 비측 교란이 얼마나 강해야 결론이 뒤집히는가"
        },
        {
          "slug": "ch20-03-s203",
          "source": "chapters/ch20-03-s203.md",
          "label": "",
          "title": "20.3 Manski 부분 식별의 직관"
        },
        {
          "slug": "ch20-04-s204",
          "source": "chapters/ch20-04-s204.md",
          "label": "",
          "title": "20.4 민감도 분석을 연구 보고의 표준으로"
        }
      ]
    },
    {
      "id": "part-6",
      "title": "제6부 | 기계학습과 인과추론",
      "description": "기계학습의 기본 도구와 인과추론의 결합 방법을 소개합니다.",
      "chapters": [
        {
          "slug": "ch21-00-ml-foundations",
          "source": "chapters/ch21-00-ml-foundations.md",
          "label": "21",
          "title": "21장. 기계학습 방법의 이해"
        },
        {
          "slug": "ch21-01-causal-ml",
          "source": "chapters/ch21-01-causal-ml.md",
          "label": "",
          "title": "21.1 예측과 인과의 목표 차이"
        },
        {
          "slug": "ch21-02-s212",
          "source": "chapters/ch21-02-s212.md",
          "label": "",
          "title": "21.2 DML과 직교화"
        },
        {
          "slug": "ch21-03-s213",
          "source": "chapters/ch21-03-s213.md",
          "label": "",
          "title": "21.3 AIPW와 이중견고성"
        },
        {
          "slug": "ch21-04-s214",
          "source": "chapters/ch21-04-s214.md",
          "label": "",
          "title": "21.4 인과 숲과 CATE"
        },
        {
          "slug": "ch21-05-s215",
          "source": "chapters/ch21-05-s215.md",
          "label": "",
          "title": "21.5 표현학습·신경망과 인과"
        }
      ]
    },
    {
      "id": "part-7",
      "title": "제7부 | 박사 수준: 반모수 이론과 효율성",
      "description": "영향함수, 효율성 경계, 부트스트랩과 부분식별의 고급 주제를 다룹니다.",
      "chapters": [
        {
          "slug": "ch22-01-influence-function-pathwise-derivative",
          "source": "chapters/ch22-01-influence-function-pathwise-derivative.md",
          "label": "",
          "title": "22.1 함수형 파라미터와 비모수 추정"
        },
        {
          "slug": "ch22-02-s222",
          "source": "chapters/ch22-02-s222.md",
          "label": "",
          "title": "22.2 영향함수(IF)와 Gateaux 미분 직관"
        },
        {
          "slug": "ch22-03-s223",
          "source": "chapters/ch22-03-s223.md",
          "label": "",
          "title": "22.3 경로미분과 효율적 추정량 도출"
        },
        {
          "slug": "ch23-01-semiparametric-efficiency-bound",
          "source": "chapters/ch23-01-semiparametric-efficiency-bound.md",
          "label": "23",
          "title": "23.1 장의 핵심 항목"
        },
        {
          "slug": "ch23-02-s231",
          "source": "chapters/ch23-02-s231.md",
          "label": "",
          "title": "23.1.1 반모수 모형의 정의와 사례"
        },
        {
          "slug": "ch23-03-s232",
          "source": "chapters/ch23-03-s232.md",
          "label": "",
          "title": "23.1.2 Cramér-Rao 한계의 반모수 확장"
        },
        {
          "slug": "ch23-04-s233",
          "source": "chapters/ch23-04-s233.md",
          "label": "",
          "title": "23.1.3 효율적 점수(efficient score)와 접선 공간(tangent space)"
        },
        {
          "slug": "ch23-05-s234",
          "source": "chapters/ch23-05-s234.md",
          "label": "",
          "title": "23.1.4 ATE 추정의 반모수 효율 한계 — 도출 과정"
        },
        {
          "slug": "ch24-01-bootstrap-failures",
          "source": "chapters/ch24-01-bootstrap-failures.md",
          "label": "24",
          "title": "24.1 장의 핵심 항목"
        },
        {
          "slug": "ch24-02-s241",
          "source": "chapters/ch24-02-s241.md",
          "label": "",
          "title": "24.1.1 표준 부트스트랩의 타당성 조건"
        },
        {
          "slug": "ch24-03-s242",
          "source": "chapters/ch24-03-s242.md",
          "label": "",
          "title": "24.1.2 부트스트랩이 실패하는 경우 — 비정칙(non-regular) 추정량, 경계 문제"
        },
        {
          "slug": "ch24-04-s243",
          "source": "chapters/ch24-04-s243.md",
          "label": "",
          "title": "24.1.3 서브샘플링(subsampling)과 m-out-of-n 부트스트랩"
        },
        {
          "slug": "ch24-05-s244",
          "source": "chapters/ch24-05-s244.md",
          "label": "",
          "title": "24.1.4 이중 기계학습에서의 교차 적합(cross-fitting)과 부트스트랩"
        },
        {
          "slug": "ch25-01-partial-identification-framework",
          "source": "chapters/ch25-01-partial-identification-framework.md",
          "label": "25",
          "title": "25.1 장의 핵심 항목"
        },
        {
          "slug": "ch25-02-s251",
          "source": "chapters/ch25-02-s251.md",
          "label": "",
          "title": "25.1.1 식별 집합(identification region)의 정의와 구성"
        },
        {
          "slug": "ch25-03-s252",
          "source": "chapters/ch25-03-s252.md",
          "label": "",
          "title": "25.1.2 단조 처치 반응(MTR) · 단조 도구변수(MIV) 가정"
        },
        {
          "slug": "ch25-04-s253",
          "source": "chapters/ch25-04-s253.md",
          "label": "",
          "title": "25.1.3 Balke-Pearl 경계, Manski 경계의 계산"
        },
        {
          "slug": "ch25-05-s254",
          "source": "chapters/ch25-05-s254.md",
          "label": "",
          "title": "25.1.4 부분 식별 결과의 보고와 해석"
        },
        {
          "slug": "ch26-01-reproducibility-checklist",
          "source": "chapters/ch26-01-reproducibility-checklist.md",
          "label": "26",
          "title": "26.1 장의 핵심 항목"
        },
        {
          "slug": "ch26-02-s261",
          "source": "chapters/ch26-02-s261.md",
          "label": "",
          "title": "26.1.1 연구 질문·식별 가정·추정 절차의 일관성 점검"
        },
        {
          "slug": "ch26-03-s262",
          "source": "chapters/ch26-03-s262.md",
          "label": "",
          "title": "26.1.2 사전분석계획(pre-analysis plan)과 분석 자유도 관리"
        },
        {
          "slug": "ch26-04-s263",
          "source": "chapters/ch26-04-s263.md",
          "label": "",
          "title": "26.1.3 재현 가능 보고 표준: 코드·데이터·민감도 공개"
        },
        {
          "slug": "ch26-05-s264",
          "source": "chapters/ch26-05-s264.md",
          "label": "",
          "title": "26.1.4 정책 해석에서 내부·외부 타당도의 분리 보고"
        }
      ]
    },
    {
      "id": "part-8",
      "title": "부록",
      "description": "",
      "chapters": [
        {
          "slug": "app-a",
          "source": "chapters/app-a.md",
          "label": "부록 A",
          "title": "부록 A. 확률론 기초 복습 — 조건부 기댓값 · 측도론 직관"
        },
        {
          "slug": "app-b",
          "source": "chapters/app-b.md",
          "label": "부록 B",
          "title": "부록 B. 선형 대수와 회귀의 기하학"
        },
        {
          "slug": "app-c",
          "source": "chapters/app-c.md",
          "label": "부록 C",
          "title": "부록 C. 주요 추정량 정리 및 가정 비교표"
        },
        {
          "slug": "app-d",
          "source": "chapters/app-d.md",
          "label": "부록 D",
          "title": "부록 D. R · Python 실습 코드 (장별)"
        },
        {
          "slug": "app-e",
          "source": "chapters/app-e.md",
          "label": "부록 E",
          "title": "부록 E. 연습 문제 해답"
        }
      ]
    },
    {
      "id": "part-9",
      "title": "참고문헌",
      "description": "이 책에서 직접 인용하거나 핵심적으로 참고한 문헌을 APA 스타일로 정리한다.",
      "chapters": [
        {
          "slug": "references",
          "source": "chapters/references.md",
          "label": "",
          "title": "참고문헌"
        }
      ]
    }
  ]
}
